signals/__init__.py
signals/__main__.py
signals/helpers.py
signals/logging.py
signals/main.py
signals/settings.py
signals/generators/__init__.py
signals/generators/base/__init__.py
signals/generators/base/base_generator.py
signals/generators/base/base_parameters.py
signals/generators/base/base_template.py
signals/generators/base/base_template_methods.py
signals/generators/ios/__init__.py
signals/generators/ios/conversion.py
signals/generators/ios/core_data.py
signals/generators/ios/ios_generator.py
signals/generators/ios/ios_template_methods.py
signals/generators/ios/objc/__init__.py
signals/generators/ios/objc/parameters.py
signals/generators/ios/objc/template.py
signals/generators/ios/objc/template_methods.py
signals/generators/ios/swift/__init__.py
signals/generators/ios/swift/parameters.py
signals/generators/ios/swift/template.py
signals/generators/ios/swift/template_methods.py
signals/generators/ios/templates/objc/api_method.j2
signals/generators/ios/templates/objc/data_model.h.j2
signals/generators/ios/templates/objc/data_model.m.j2
signals/generators/ios/templates/objc/entity_mapping.j2
signals/generators/ios/templates/objc/relationship_mapping.j2
signals/generators/ios/templates/objc/descriptors/request.j2
signals/generators/ios/templates/objc/descriptors/response.j2
signals/generators/ios/templates/objc/methods/parameters.j2
signals/generators/ios/templates/objc/methods/request.j2
signals/generators/ios/templates/objc/methods/send_object.j2
signals/generators/ios/templates/swift/api_method.j2
signals/generators/ios/templates/swift/data_model.swift.j2
signals/generators/ios/templates/swift/entity_mapping.j2
signals/generators/ios/templates/swift/relationship_mapping.j2
signals/generators/ios/templates/swift/descriptors/request.j2
signals/generators/ios/templates/swift/descriptors/response.j2
signals/generators/ios/templates/swift/methods/parameters.j2
signals/generators/ios/templates/swift/methods/request.j2
yak_signals-0.2.8.dist-info/DESCRIPTION.rst
yak_signals-0.2.8.dist-info/entry_points.txt
yak_signals-0.2.8.dist-info/METADATA
yak_signals-0.2.8.dist-info/metadata.json
yak_signals-0.2.8.dist-info/pbr.json
yak_signals-0.2.8.dist-info/RECORD
yak_signals-0.2.8.dist-info/top_level.txt
yak_signals-0.2.8.dist-info/WHEEL
