Metadata-Version: 2.0
Name: yak-signals
Version: 0.2.8
Summary: A tool for auto generating libraries for different platforms to communicate with your API
Home-page: https://github.com/yeti/signals/
Author: Rudy Mutter
Author-email: support@yeti.co
License: MIT
Platform: UNKNOWN
Classifier: Development Status :: 3 - Alpha
Classifier: Environment :: Console
Classifier: Intended Audience :: Developers
Classifier: Programming Language :: Python
Classifier: Programming Language :: Python :: 2
Classifier: Programming Language :: Python :: 2.6
Classifier: Programming Language :: Python :: 2.7
Classifier: Topic :: Software Development
Classifier: Topic :: Software Development :: Build Tools
Classifier: Topic :: Software Development :: Libraries :: Python Modules
Requires-Dist: click (>=4.0)
Requires-Dist: lxml (>=3.4)
Requires-Dist: Jinja2 (>=2.7.3)
